{
    "recipes": [
        {
            "id": "work_commandjob_d",
            "label": "换成大额纸币",
            "actionId": "work_r",
            "effects": {
                "lmfunds": -5,
                "lmfunds_b": 1
            },
            "startdescription": "换好了",
            "description": "已经换好了。",
            "warmup": 10,
            "craftable": false
        },
        {
            "id": "lufunds_stackup_c",
            "label": "足够的零钱",
            "actionId": "work_r",
            "requirements": {
                "lmfunds": 5
            },
            "startdescription": "可以了，已经够了",
            "description": ".",
            "warmup": 10,
            "craftable": false,
            "linked": [
                {
                    "id": "work_commandjob_d",
                    "chance": 100
                }
            ]
        },
        {
            "id": "lufunds_stackup_b2",
            "label": "零钱不够",
            "actionId": "work_r",
            "requirements": {},
            "startdescription": "零钱不够",
            "description": ".",
            "warmup": 10,
            "craftable": false
        },
        {
            "id": "lufunds_stackup_b1",
            "label": "需要更多零钱",
            "actionId": "work_r",
            "extantreqs": {
                "lmfunds": 5
            },
            "slots": [
                {
                    "id": "needlmfunds",
                    "label": "龙门币",
                    "description": "更多龙门币",
                    "required": {
                        "lmfunds": 1
                    },
                    "greedy": true
                }
            ],
            "startdescription": "需要更多零钱才能换成大额纸币",
            "description": "继续",
            "warmup": 2,
            "craftable": false,
            "linked": [
                {
                    "id": "lufunds_stackup_b1",
                    "chance": 100
                },
                {
                    "id": "lufunds_stackup_b2",
                    "chance": 100
                }
            ],
            "alt": [
                {
                    "id": "lufunds_stackup_c",
                    "chance": 100
                }
            ]
        },
        {
            "id": "lufunds_stackup_a",
            "label": "把10张<b>龙门币</b>换成<b>大额龙门币</b>",
            "actionId": "work_r",
            "requirements": {
                "lmfunds": 1
            },
            "startdescription": "我把零钱交给干员。",
            "description": ".",
            "warmup": 10,
            "craftable": true,
            "linked": [
                {
                    "id": "lufunds_stackup_b1",
                    "chance": 100
                },
                {
                    "id": "lufunds_stackup_b2",
                    "chance": 100
                }
            ]
        }
    ]
}